{
  "data": [
    {
      "bin": [
        0.0, 
        0.9
      ], 
      "values": [
        {
          "bin": [
            20.0, 
            25.0
          ], 
          "error_low": 0.003507531194898018, 
          "value": 0.9733522534370422, 
          "error_high": 0.003507531194898018
        }, 
        {
          "bin": [
            25.0, 
            30.0
          ], 
          "error_low": 0.0016304189969393375, 
          "value": 0.9855405688285828, 
          "error_high": 0.0016304189969393375
        }, 
        {
          "bin": [
            30.0, 
            40.0
          ], 
          "error_low": 0.0005632347862981866, 
          "value": 0.9912209510803223, 
          "error_high": 0.0005632347862981866
        }, 
        {
          "bin": [
            40.0, 
            50.0
          ], 
          "error_low": 0.00040197664605401824, 
          "value": 0.9920125603675842, 
          "error_high": 0.00040197664605401824
        }, 
        {
          "bin": [
            50.0, 
            60.0
          ], 
          "error_low": 0.0010644249313712401, 
          "value": 0.9879141449928284, 
          "error_high": 0.0010644249313712401
        }, 
        {
          "bin": [
            60.0, 
            120.0
          ], 
          "error_low": 0.0018967601062150053, 
          "value": 0.9896888136863708, 
          "error_high": 0.0018967601062150053
        }
      ]
    }, 
    {
      "bin": [
        0.9, 
        1.2
      ], 
      "values": [
        {
          "bin": [
            20.0, 
            25.0
          ], 
          "error_low": 0.005026487551713813, 
          "value": 0.98630690574646, 
          "error_high": 0.005026487551713813
        }, 
        {
          "bin": [
            25.0, 
            30.0
          ], 
          "error_low": 0.0029515074138158903, 
          "value": 0.9911109805107117, 
          "error_high": 0.0029515074138158903
        }, 
        {
          "bin": [
            30.0, 
            40.0
          ], 
          "error_low": 0.0009835063202250365, 
          "value": 0.9927794933319092, 
          "error_high": 0.0009835063202250365
        }, 
        {
          "bin": [
            40.0, 
            50.0
          ], 
          "error_low": 0.0007182040260755296, 
          "value": 0.9950618743896484, 
          "error_high": 0.0007182040260755296
        }, 
        {
          "bin": [
            50.0, 
            60.0
          ], 
          "error_low": 0.0017571173984507712, 
          "value": 0.9939614534378052, 
          "error_high": 0.0017571173984507712
        }, 
        {
          "bin": [
            60.0, 
            120.0
          ], 
          "error_low": 0.003267600836076229, 
          "value": 0.9841365814208984, 
          "error_high": 0.003267600836076229
        }
      ]
    }, 
    {
      "bin": [
        1.2, 
        2.1
      ], 
      "values": [
        {
          "bin": [
            20.0, 
            25.0
          ], 
          "error_low": 0.0028421174318538794, 
          "value": 0.9974881410598755, 
          "error_high": 0.0028421174318538794
        }, 
        {
          "bin": [
            25.0, 
            30.0
          ], 
          "error_low": 0.0016078610689727975, 
          "value": 0.9939442276954651, 
          "error_high": 0.0016078610689727975
        }, 
        {
          "bin": [
            30.0, 
            40.0
          ], 
          "error_low": 0.0006052138672063449, 
          "value": 0.994232177734375, 
          "error_high": 0.0006052138672063449
        }, 
        {
          "bin": [
            40.0, 
            50.0
          ], 
          "error_low": 0.0001886594212133765, 
          "value": 0.9955248832702637, 
          "error_high": 0.0001886594212133765
        }, 
        {
          "bin": [
            50.0, 
            60.0
          ], 
          "error_low": 0.0011737013649394767, 
          "value": 0.9928236603736877, 
          "error_high": 0.0011737013649394767
        }, 
        {
          "bin": [
            60.0, 
            120.0
          ], 
          "error_low": 0.002681003795368408, 
          "value": 0.9852241277694702, 
          "error_high": 0.002681003795368408
        }
      ]
    }, 
    {
      "bin": [
        2.1, 
        2.4
      ], 
      "values": [
        {
          "bin": [
            20.0, 
            25.0
          ], 
          "error_low": 0.006046268162933127, 
          "value": 0.9786626696586609, 
          "error_high": 0.006046268162933127
        }, 
        {
          "bin": [
            25.0, 
            30.0
          ], 
          "error_low": 0.003799613273442326, 
          "value": 0.9680444598197937, 
          "error_high": 0.003799613273442326
        }, 
        {
          "bin": [
            30.0, 
            40.0
          ], 
          "error_low": 0.0018302561245198258, 
          "value": 0.970801055431366, 
          "error_high": 0.0018302561245198258
        }, 
        {
          "bin": [
            40.0, 
            50.0
          ], 
          "error_low": 0.001687416973278098, 
          "value": 0.9681301116943359, 
          "error_high": 0.001687416973278098
        }, 
        {
          "bin": [
            50.0, 
            60.0
          ], 
          "error_low": 0.004284416854361719, 
          "value": 0.972404956817627, 
          "error_high": 0.004284416854361719
        }, 
        {
          "bin": [
            60.0, 
            120.0
          ], 
          "error_low": 0.009477497957824184, 
          "value": 0.9361975193023682, 
          "error_high": 0.009477497957824184
        }
      ]
    }
  ], 
  "dimension": 2, 
  "binning": {
    "y": [
      20.0, 
      25.0, 
      30.0, 
      40.0, 
      50.0, 
      60.0, 
      120.0
    ], 
    "x": [
      0.0, 
      0.9, 
      1.2, 
      2.1, 
      2.4
    ]
  }
}